Workbook

Sheet Summary
A1: SKB Rice Mundy — QA Round 4 (full sweep)
A2: App: https://skb-rice-mundy-3ca47.web.app · Tested 7 Sep 2026 IST · Microsoft Edge · signed in as Owner (santhoshbalamani@gmail.com)
A4: What this round covered
A5: A full pass over every module, plus the two paths round 3 listed as never exercised: the sale EDIT path and the supplier ledger PAYMENT EDIT. Both were tested for the first time. The payment edit turned out to be broken.
A7: Measure | B7: Count | C7: Notes
A8: Test cases executed this round | B8: =COUNTA('Round 4 results'!$E$4:$E$27) -> 24 | C8: Counted from the 'Round 4 results' tab, not typed in
A9: Passed | B9: =COUNTIF('Round 4 results'!$E$4:$E$27,"PASS") -> 19 | C9: Computed from this workbook's own data
A10: Failed | B10: =COUNTIF('Round 4 results'!$E$4:$E$27,"FAIL") -> 5 | C10: Computed from this workbook's own data
A11: Blocked | B11: =COUNTIF('Round 4 results'!$E$4:$E$27,"BLOCKED") -> 0 | C11: Computed from this workbook's own data
A12: New defects raised | B12: =COUNTA(Defects!$A$4:$A$7) -> 4 | C12: Computed from this workbook's own data
A13: Automated tests in the suite | B13: 92 | C13: Was 78 at the end of round 3. 14 added this round.
A15: The headline
A16: • | B16: Two critical money defects were found, both in code the client has been running.
B17: Neither was introduced by this project's changes. Item editing has never worked at all; editing a supplier payment corrupts the ledger row and the balance together, and the two then disagree about which is wrong.
A19: • | B19: Everything the last two rounds fixed held up under a fresh pass.
B20: The derived running balance (NEW-07), the orphaned-category surfacing (NEW-06), the future-date guards (BUG-10) and the deletion cascades were all re-exercised against live data and all behaved.
A22: • | B22: Stock and money reconcile everywhere they are shown.
B23: 18 items / 8,301 bags / Rs 1,22,09,350 agreed across Inventory, two reports and the Dashboard, re-summed independently row by row rather than read off a total. Outstanding of Rs 1,41,85,975 agreed across four screens.
A25: • | B25: The app cannot yet do the thing round 3 set out to fix.
B26: The three 'Hmt Boiled' records still cannot be renamed on the live site, because the item-edit defect below blocks every item save. The fix is committed and waiting on a deploy.

Sheet Round 4 results
A1: Round 4 — test cases executed
A2: Every figure below was read off the live app. Totals marked 're-summed' were recomputed row by row in the page, not read from the app's own total.
A3: ID | B3: Area | C3: What was tested | D3: What was observed | E3: Result | F3: Links to
A4: R4-01 | B4: Dashboard | C4: Date rollover across midnight IST | D4: Today's Sales reset to Rs 0; yesterday's Rs 10,000 bill relabelled 'Yesterday'; 7-day window advanced Tue→Mon; week total still Rs 10,000 | E4: PASS
A5: R4-02 | B5: Inventory | C5: Header total vs the rows actually rendered | D5: Re-summed the rendered rows in the page: 18 items / 8,297 bags, matching the header exactly | E5: PASS | F5: NEW-06
A6: R4-03 | B6: Sales | C6: Record a sale (4 bags Sona Raw @ 1,750) | D6: Bill SKB-2026-0029 Rs 7,000. Stock 260→256, total bags 8,297→8,293 | E6: PASS
A7: R4-04 | B7: Sales | C7: EDIT that sale to 6 bags — untested since round 1 | D7: Confirm dialog names the effect. Bill Rs 10,500 / 6 bags; stock →254; total 8,291 = 8,297-6, so the 4 was fully reversed rather than double-counted; customer balance Rs 10,500; ONE ledger row | E7: PASS
A8: R4-05 | B8: Ledger | C8: Business ledger after the edit | D8: One row, 07 Sept, Sale, debit Rs 10,500. Net balance 1,41,75,475 → 1,41,85,975, exactly +10,500 | E8: PASS
A9: R4-06 | B9: Purchase | C9: Record a purchase (10 bags Motta Raw @ 1,100) | D9: PUR-2026-0004 Rs 11,000 UNPAID. Motta Raw 6→16; total bags 8,291→8,301; re-summed rows = header exactly | E9: PASS
A10: R4-07 | B10: Purchase | C10: Future-date guard on the purchase form | D10: Date input carries max=2026-09-07 | E10: PASS | F10: BUG-10
A11: R4-08 | B11: Supplier | C11: Supplier ledger running balance | D11: Three dated rows accumulate correctly, and two same-day rows order bill-then-payment | E11: PASS | F11: NEW-07
A12: R4-09 | B12: Supplier | C12: Record a supplier payment of Rs 4,000 | D12: Header 11,000→7,000; row credit Rs 4,000; balance Rs 7,000 | E12: PASS
A13: R4-10 | B13: Supplier | C13: EDIT that payment to Rs 6,000 — never exercised before | D13: Row became debit Rs 6,000 AND credit Rs 4,000; statement Rs 13,000; header Rs 1,000; correct is Rs 5,000 | E13: FAIL | F13: R4-D3
A14: R4-11 | B14: Reports | C14: Supplier Balance Report after the bad edit | D14: Reports 'paid Rs 10,000' — it is summing both sides of the corrupted row. Confirms the damage reaches reporting | E14: FAIL | F14: R4-D3
A15: R4-12 | B15: Masters | C15: Rename an item (the whole point of round 3) | D15: Item Name field is now editable — the round 3 fix is live. But Save fails: 'Item name is required.' Seven attempts, seven identical server-side errors | E15: FAIL | F15: R4-D2
A16: R4-13 | B16: Deploy | C16: Which bundle the live site serves | D16: index.html referenced the new bundle, but this browser ran the old one from cache; the old bundle no longer exists and the SPA rewrite returns index.html for it at status 200 | E16: FAIL | F16: R4-D1
A17: R4-14 | B17: Reports | C17: Current Stock Report reconciliation | D17: 18 rows, re-summed = 8,301 bags / Rs 1,22,09,350 = the printed total and the Inventory header | E17: PASS
A18: R4-15 | B18: Reports | C18: Stock Summary by Variety | D18: 4+1+2+10+1 = 18 items; 5,963+1,038+874+422+4 = 8,301; values foot to Rs 1,22,09,350; cross-foots against Current Stock category by category. No orphan 'boiled-rice' row | E18: PASS | F18: NEW-06
A19: R4-16 | B19: Reports | C19: Customer-wise Balance | D19: 86 rows, re-summed = Rs 1,41,85,975 = the printed total = the Ledger net balance = the Reports header | E19: PASS
A20: R4-17 | B20: Reports | C20: Item-wise Sales Data | D20: Sona Raw 1 bill / 6 bags / 156 kg / Rs 10,500 — the EDITED figure, with no ghost 4-bag row. Totals foot | E20: PASS
A21: R4-18 | B21: Reports | C21: Category-wise Purchase vs Sale (P&L) | D21: Avg sell 20,500/16 = 1,281.25; profit (1,281.25-1,100)x16 = Rs 2,900; margin 2,900/20,500 = 14.15%. All three recomputed by hand and correct | E21: PASS
A22: R4-19 | B22: Customers | C22: Statement after deleting the bill — the round 3 defect | D22: Surviving payment row shows -Rs 3,000, derived. Header reads 'Advance Balance Rs 3,000'. Before the fix this row kept printing the pre-deletion figure | E22: PASS | F22: NEW-07
A23: R4-20 | B23: Sales | C23: Delete a bill restores stock | D23: Sona Raw 254→260; totals 8,301→8,307; full arc 260→256→254→260 reversed exactly | E23: PASS
A24: R4-21 | B24: Customers | C24: Delete customer cascade | D24: Requires typing the exact name. Count 86→85, no residual rows, and the ledger net balance returned to Rs 1,41,75,475 — the exact pre-test figure | E24: PASS | F24: BUG-23
A25: R4-22 | B25: Masters | C25: Delete an item that still holds stock | D25: Warned '7 bags in stock ... make sure stock is accounted for', then Delete Anyway. Removed cleanly | E25: PASS
A26: R4-23 | B26: Masters | C26: Delete or rename a category | D26: No such control exists, and no deleteCategory anywhere in the source. A category, once created, is permanent inside the app | E26: FAIL | F26: R4-D4
A27: R4-24 | B27: Ledger | C27: Date filter with opening and closing balance rows | D27: Filtered 15 Aug: 9 entries bracketed by Opening Rs 1,43,14,975 and Closing Rs 1,42,05,475. Walked every row — the seven transactions carry one figure to the other exactly | E27: PASS
A29: Totals | C29: =CONCATENATE(COUNTIF(E4:E27,"PASS")," pass / ",COUNTIF(E4:E27,"FAIL")," fail of ",COUNTA(E4:E27)," executed") -> 19 pass / 5 fail of 24 executed

Sheet Defects
A1: Defects raised in round 4
A2: All four are in code the client has been running. None was introduced by this project's changes — the item-edit defect was merely uncovered by unlocking the name field.
A3: ID | B3: Severity | C3: Title | D3: What happens, and why | E3: Fix | F3: Status
A4: R4-D2 | B4: Critical | C4: No item could be edited, ever | D4: AddItemModal called updateItem(id, {categoryKey, bagKg, mrp}) with no name. updateItem treats a missing name as blank and throws 'Item name is required.', so EVERY item edit failed — a plain MRP, bag-size or category correction included, not only a rename. Original code (9f571ac). The disabled Item Name field hid it: the field looked deliberately read-only rather than silently unsent. Confirmed in the console: 7 attempts, 7 identical server-side errors. | E4: Send name with the payload. The catch also flattened every failure to 'Failed to save item', hiding the actionable 'An item with the name X already exists.' — it now shows the real reason. New test goes through the MODAL, not updateItem in isolation, which is why the existing rename test never caught this. | F4: Fixed in d109cd0 — awaiting deploy
A5: R4-D3 | B5: Critical | C5: Supplier payment edit writes to the DEBIT side | D5: Both recordSupplierPayment and recordPayment store a payment as {debit: 0, credit: amount}. editLedgerEntry branched on isSupplier, read the old amount off debit (always 0) and wrote the new amount to debit as well, leaving the original credit in place. So the row claimed both sides, and the balance was reduced by the whole new amount a second time. Live: Rs 11,000 bill, Rs 4,000 paid, edited to Rs 6,000 → row 6,000/4,000, statement Rs 13,000, header Rs 1,000, report 'paid Rs 10,000'. Correct: Rs 5,000. The customer path was unaffected. | E5: The branch is gone — a payment is a credit for both. Beyond that the balance is now RECOMPUTED from the person's rows rather than nudged by a delta, in both edit and delete: a delta is only right while the stored figure is, and this function corrupted that figure, so a skewed balance would otherwise never recover. The damaged Kalambur AMK record now repairs itself on the next edit or delete of that payment. | F5: Fixed in 9e8c5b6 — awaiting deploy
A6: R4-D1 | B6: High | C6: Every deploy risks a blank page for returning users | D6: firebase.json set no Cache-Control, so Firebase served index.html with max-age=3600. For an hour after any deploy a returning user runs the old app — and the old content-hashed bundle is gone, so the '**' → /index.html rewrite answers the request for it with index.html at status 200. With the existing nosniff header the browser refuses to execute it and the user sees a blank page, recoverable only by a hard refresh. This session hit it mid-test, which is how it was found. | E6: index.html is now no-cache/no-store/must-revalidate; /assets/** is immutable for a year, which is safe because those filenames are content-hashed. Confirmed against the live site before fixing: status 200, HTML body, cache-control max-age=3600, nosniff. | F6: Fixed in d109cd0 — awaiting deploy
A7: R4-D4 | B7: Medium | C7: A category can be created but never deleted or renamed | D7: There is no deleteCategory anywhere in src/, and no delete or rename control in Item Masters — only Add Category inside the Add Item modal. This is also how round 4's NEW-06 orphan happened: the duplicate 'Boiled Rice' category was removed from the FIREBASE CONSOLE, not the app, so nothing re-pointed its item and 400 bags / Rs 3,60,000 went invisible. While the console is the only way to remove a category, that will recur. | E7: Not fixed — this one needs a decision first. What should happen to items in a category being deleted: block the delete while any item points at it, or force them to be re-pointed? The itemGrouping fix already surfaces orphans instead of hiding them, so the damage is contained either way. | F7: Open — needs a client decision

Sheet Post-deploy
A1: After the deploy — what was verified on the live site
A2: Bundle index-WOZfADgy.js. Everything below was re-checked against the running app, not against the code. This tab supersedes the 'awaiting deploy' statuses on the Defects and All rounds tabs.
A4: ID | B4: What | C4: Before | D4: After | E4: Result
A5: R4-D1 | B5: Cache headers on the live site | C5: index.html: max-age=3600, and the old bundle 404'd into index.html at status 200 → blank page | D5: index.html: no-cache, no-store, must-revalidate. /assets/**: public, max-age=31536000, immutable | E5: PASS
A6: R4-D2 | B6: Rename the three duplicate item records | C6: Every item save failed with 'Item name is required.' — 7 attempts, 7 server-side errors | D6: All three renamed: HMT Boiled (4,922), HMT Boiled - Carshed (774), HMT Boiled - Godown (1,038). The Carshed record's trailing space was trimmed | E6: PASS
A7: R4-D2 | B7: Item editing in general | C7: No item could be edited at all — MRP, bag size or category included | D7: Item editing works for the first time. This was the blocker on the whole round 3 objective | E7: PASS
A8: R4-D3 | B8: Edit the Kalambur AMK supplier payment | C8: Row: debit 6,000 AND credit 4,000. Statement 13,000. Header 1,000. Report 'paid 10,000' | D8: Row: credit 6,000, balance 5,000. Header 5,000. Report: purchased 11,000 / paid 6,000 / payable 5,000. Tile 5,000 | E8: PASS
A9: R4-D3 | B9: Do the four sources agree? | C9: Every one of them disagreed, and each was wrong differently | D9: All four agree, and agree on the correct figure of Rs 5,000 | E9: PASS
A10: R4-D3 | B10: Self-repair of the damaged record | C10: The corrupted row and the skewed stored balance both persisted through a reload | D10: Both healed on a single edit, with no data migration — the recompute working as designed | E10: PASS
A11: e9e44d2 | B11: The hang I introduced, then fixed | C11: The same edit sat on 'Saving...' indefinitely: no error, no toast, nothing written | D11: Completed in about 7 seconds | E11: PASS
A12: — | B12: Delete the two stale Sona Raw test records | C12: Two zero-stock duplicates left over from round 1 | D12: Both deleted. Only the real 260-bag record remains | E12: PASS
A13: — | B13: Duplicate item names anywhere in the app | C13: HMT Boiled x3, Sona Raw x3 — indistinguishable in every picker | D13: ZERO duplicates. The purchase item picker lists 16 items, every one uniquely identifiable. The mis-billing risk is closed | E13: PASS
A14: — | B14: Inventory reconciliation after all the changes | C14: 18 items / 8,301 bags | D14: 16 items / 8,307 bags, re-summed row by row and matching the header exactly. The two deleted records held no stock | E14: PASS
A15: R4-D4 | B15: Delete or rename a category | C15: No control, and no deleteCategory in the source | D15: Unchanged — still open, and still needs a decision on what happens to items in a deleted category | E15: OPEN
A17: Verified | B17: =CONCATENATE(COUNTIF(E5:E15,"PASS")," of ",COUNTA(E5:E15)," verified on the live site; ",COUNTIF(E5:E15,"OPEN")," still open") -> 10 of 11 verified on the live site; 1 still open
A19: One thing I got wrong, and how
A20: The balance recompute I shipped in 9e8c5b6 ran its Firestore query from inside the transaction. A query issued there can block on the same stream the transaction holds, so the payment edit hung on 'Saving...' forever — no error, no toast, no console entry, nothing written. I hit it on my first attempt to repair Kalambur AMK. All eight of my tests passed while the feature was unusable, because they tested the arithmetic and never the mechanics. Fixed in e9e44d2 by reading the ledger once before the transaction opens, with two tests that pin the ordering specifically: moving the read back inside turns one red while the other nine stay green.

Sheet All rounds
A1: Defect history across all four rounds
A2: Status as of 7 Sep 2026. 'Fixed, verified' means re-exercised against the live app after the fix was deployed.
A3: ID | B3: Round | C3: Severity | D3: Title | E3: Resolution | F3: Status
A4: NEW-01 | B4: 2 | C4: Critical | D4: Every write to items was denied | E4: Rules separated stock movement from master-data edit; isStockOnlyUpdate() added; inventory_adjustments given a rule; isOwner() guarded with exists() | F4: Fixed, verified round 3
A5: BUG-02 | B5: 1 | C5: Critical | D5: Two different stock totals (6,033 vs 8,317) | E5: getUniqueActiveItems de-duplicated by name and discarded the stock with it. Replaced by getActiveItems | F5: Fixed, verified round 3
A6: BUG-23 | B6: 1 | C6: Critical | D6: Customer delete cascade never ran | E6: Blocked by NEW-01. Executed for the first time in round 3; re-verified this round | F6: Fixed, verified round 4
A7: BUG-20 | B7: 1 | C7: Medium | D7: Overdue was meaningless, then contradictory | E7: Ageing runs from lastPayment or lastPurchase or createdAt; gross, advance and net reported separately | F7: Fixed, verified round 3
A8: NEW-03 | B8: 2 | C8: Low | D8: rate: NaN written into every sale line | E8: Finite-checked toNum() on every numeric field | F8: Fixed, verified round 3
A9: NEW-04 | B9: 2 | C9: Low | D9: Mobile length unvalidated ('12' saved) | E9: 7-15 digit range check | F9: Fixed, verified round 3
A10: NEW-05 | B10: 2 | C10: Low | D10: Global search could not find a bill | E10: searchSalesByBillNo() prefix query plus a Bills section | F10: Fixed, verified round 3
A11: BUG-18 | B11: 1 | C11: Low | D11: '1 transactions' | E11: Customers page now matches CustomersList's plural logic | F11: Fixed, verified round 3
A12: BUG-16 | B12: 1 | C12: Low | D12: Suppliers could not be deleted | E12: deleteSupplier() added, guarded like deleteItem | F12: Fixed, verified round 3
A13: NEW-06 | B13: 3 | C13: High | D13: Items whose category was deleted became unmanageable | E13: 400 bags / Rs 3,60,000 counted in every total but rendered in no editable table. Both copies of the grouping replaced by utils/itemGrouping.js, which surfaces orphans | F13: Fixed, verified round 4
A14: NEW-07 | B14: 3 | C14: High | D14: Customer statement went stale after any deletion | E14: Stored balanceAfter was never rewritten on delete. Now derived on read in utils/ledgerBalance.js; repairs already-corrupted statements with no migration | F14: Fixed, verified round 4
A15: BUG-10 | B15: 3 | C15: Medium | D15: Future-dated transactions | E15: max= added to all five date inputs; three forms that had no save guard at all now refuse a future date | F15: Fixed, verified round 4
... A21: D6-01 | B21: 4 | C21: High | D21: Balance recompute hung the payment edit | E21: My own regression in 9e8c5b6: the ledger query ran inside the Firestore transaction and blocked. Read hoisted out in e9e44d2 | F21: Fixed, verified round 4 (post-deploy)
A23: Counts | D23: =CONCATENATE(COUNTA($A$4:$A$21)," defects tracked across all four rounds") -> 18 defects tracked across all four rounds
D24: =CONCATENATE(COUNTIF($F$4:$F$21,"Fixed, verified round 3")," fixed and verified in round 3") -> 8 fixed and verified in round 3
D25: =CONCATENATE(COUNTIF($F$4:$F$21,"Fixed, verified round 4")," fixed and verified during round 4") -> 4 fixed and verified during round 4
D26: =CONCATENATE(COUNTIF($F$4:$F$21,"Fixed, verified round 4 (post-deploy)")," fixed and verified after the round 4 deploy") -> 5 fixed and verified after the round 4 deploy
D27: =CONCATENATE(COUNTIF($F$4:$F$21,"Open*")," still open — R4-D4, which needs a client decision") -> 1 still open — R4-D4, which needs a client decision
D28: =CONCATENATE("Buckets account for ",COUNTIF($F$4:$F$21,"Fixed, verified round 3")+COUNTIF($F$4:$F$21,"Fixed, verified round 4")+COUNTIF($F$4:$F$21,"Fixed, verified round 4 (post-deploy)")+COUNTIF($F$4:$F$21,"Open*")," of ",COUNTA($A$4:$A$21)," tracked") -> Buckets account for 18 of 18 tracked

Sheet Reconciliation
A1: Independent reconciliation of stock and money
A2: The point of this tab is that the app's own totals were never taken on trust. Each 'Re-summed' figure was recomputed row by row inside the live page; the Difference column is a live formula, so it stays honest if anyone edits this sheet.
A4: What was compared | B4: App's own total | C4: Re-summed by hand | D4: Difference | E4: Where
A5: Items in stock (count) | B5: 18 | C5: 18 | D5: =C5-B5 -> 0 | E5: Inventory header vs every rendered row
A6: Bags in stock | B6: 8301 | C6: 8301 | D6: =C6-B6 -> 0 | E6: Inventory header vs every rendered row
A7: Bags in stock — Current Stock Report | B7: 8301 | C7: 8301 | D7: =C7-B7 -> 0 | E7: Report total vs its own 18 rows
A8: Stock value (Rs) | B8: 12209350 | C8: 12209350 | D8: =C8-B8 -> 0 | E8: Current Stock Report total vs its 18 rows
A9: Stock Summary by Variety — items | B9: 18 | C9: 18 | D9: =C9-B9 -> 0 | E9: 4+1+2+10+1 across the five stocked categories
A10: Stock Summary by Variety — bags | B10: 8301 | C10: 8301 | D10: =C10-B10 -> 0 | E10: 5,963+1,038+874+422+4
A11: Customer outstanding (Rs) | B11: 14185975 | C11: 14185975 | D11: =C11-B11 -> 0 | E11: Customer-wise Balance total vs its 86 rows
A12: Sales in the range — bags | B12: 16 | C12: 16 | D12: =C12-B12 -> 0 | E12: Item-wise Sales vs Total Sales (Date-wise)
A13: Sales in the range (Rs) | B13: 20500 | C13: 20500 | D13: =C13-B13 -> 0 | E13: Item-wise Sales vs Total Sales (Date-wise)
A14: Total of all differences | D14: =SUM(D5:D13) -> 0 | E14: Anything other than zero means a screen is lying about a total.
A17: The one figure that does NOT reconcile
A18: Kalambur AMK, after the round 4 supplier payment edit (R4-D3). Recorded here as the damage this defect does, not as an arithmetic check — every figure below is wrong in a different way, which is exactly what makes the defect dangerous.
A20: Source | B20: Shows (Rs) | C20: Correct (Rs) | D20: Error (Rs) | E20: Why it differs
A21: Supplier header 'Balance Payable' | B21: 1000 | C21: 5000 | D21: =B21-C21 -> -4000 | E21: Reduced by the full Rs 6,000 again on top of the original Rs 4,000
A22: Supplier statement, latest row | B22: 13000 | C22: 5000 | D22: =B22-C22 -> 8000 | E22: Row carries debit 6,000 AND credit 4,000, so it adds instead of subtracting
A23: Supplier Balance Report, 'paid' | B23: 10000 | C23: 6000 | D23: =B23-C23 -> 4000 | E23: Sums both sides of the corrupted row
A24: Reports page tile | B24: 1000 | C24: 5000 | D24: =B24-C24 -> -4000 | E24: Reads the same corrupted stored balance as the header
A26: This self-repairs once 9e8c5b6 is deployed, on the next edit or delete of that payment, because the balance is then recomputed from the rows rather than adjusted by a delta.

Sheet Still to do
A1: What is left, and who has to do it
A2: Nothing in this list can be done from this session: the deploy endpoints (googleapis.com) are unreachable from both available shells.
A3: # | B3: Item | C3: Detail | D3: Owner
A4: 1 | B4: Deploy the three commits | C4: ed8a500, d109cd0, 9e8c5b6. From the project folder: npm run build && firebase deploy --only hosting. The firebase.json change means the headers ship with this deploy too. | D4: You — terminal
A5: 2 | B5: Rename the three 'Hmt Boiled' records | C5: Carshed (774) and Godown (1,038) so all three are distinct. Blocked until the deploy, because every item save currently fails. Note the Carshed record's stored name has a trailing space, which the rename will trim. Order matters: while duplicates exist none of them can be saved unchanged, so rename first, then any other edit works. | D5: Me — after the deploy
A6: 3 | B6: Delete the two zero-stock Sona Raw records | C6: 'Sona Raw' and 'sona raw', both 0 bags, left from round 1 testing. Same blocker. | D6: Me — after the deploy
A7: 4 | B7: Repair Kalambur AMK | C7: Edit or delete the Rs 6,000 payment once deployed; the recompute corrects the balance. Currently showing Rs 1,000 against a true Rs 5,000. | D7: Me — after the deploy
A8: 5 | B8: Remove the leftover 'ZZ Test Cat' category | C8: Created while testing R4-D4 and now unremovable from inside the app — which is the defect. Empty and harmless, but it needs a Firebase Console delete. | D8: You — Firebase Console
A9: 6 | B9: Decide what a category delete should do | C9: Block while any item points at it, or force re-pointing first? Needed before R4-D4 can be closed. | D9: Client decision
A10: 7 | B10: Rotate the Firebase test password | C10: .env.test was committed and the repo was public for a period. Deleting the file does not remove it from git history, so rotating the password is the only real fix. | D10: You / the client
A11: 8 | B11: Decide three open requirement conflicts | C11: deleteItem refuses an item with sale or purchase history; deleteSupplier refuses one with purchases; only the most recent payment is editable. The client's notes ask for deletion 'at any time'. Each has a real cost — historic bills pointing at nothing, or recomputing every later balance. | D11: Client decision

Sheet Observations
A1: Smaller things worth knowing
A2: Not defects. Recorded because each is a decision someone may want to make, or a trap for whoever tests this next.
A3: # | B3: What | C3: Detail
A4: 1 | B4: 'Last Updated' never moves for a sale | C4: A purchase moved Motta Raw's Last Updated to 07 Sept 12:38 pm. The sale and the sale edit did not move Sona Raw's, though its stock went 260→256→254. So that column means 'last purchased or adjusted', never 'last sold'. Anyone reading it to find recent movement will miss sales entirely.
A5: 2 | B5: A bill-linked payment can be deleted but not edited | C5: On the supplier ledger the standalone payment offers Edit and Delete; the payment tied to PUR-2026-0001 offers Delete only. Correcting a typo in a bill-linked payment therefore forces a delete-and-recreate — the destructive path the client's notes were trying to avoid.
A6: 3 | B6: The payment edit modal has no date field | C6: Amount, mode and note can be corrected. The payment date cannot.
A7: 4 | B7: Duplicate item names are visible everywhere | C7: The Dashboard's Stock by Variety, the sale item picker and the purchase item picker all show HMT Boiled / Hmt Boiled / Hmt Boiled and Sona Raw / Sona Raw / sona raw with nothing to tell them apart beyond stock count. This is the risk the rename was meant to remove and it is still live.
A8: 5 | B8: A double submit can hang a payment | C8: Submitting the customer payment form twice in quick succession left the button stuck on 'Recording...' and wrote nothing — two concurrent transactions contending. Caused by the test script, not reachable by a normal user: the UI already disables the button while submitting. Nothing was written and no partial state resulted. Recorded, not raised.
A9: 6 | B9: The 'edited' marker is a good touch | C9: A bill that has been edited shows as 'Bill SKB-2026-0029 (edited)' in the customer statement. Worth keeping.
A10: 7 | B10: Opening and closing balance rows are correct | C10: The ledger date filter brackets the period with Opening and Closing rows, and every transaction between them carries one figure to the other exactly. Checked row by row on 15 Aug.
